annlib.cp38-win32.pyd
pyann/__about__.py
pyann/__init__.py
pyann/nn2.py
pyann/annlib/__init__.py
pyann/tests/__init__.py
pyann/tests/test_nn2.py
pyann-0.0.1.dist-info/LICENSE
pyann-0.0.1.dist-info/METADATA
pyann-0.0.1.dist-info/WHEEL
pyann-0.0.1.dist-info/top_level.txt
pyann-0.0.1.dist-info/RECORD
