Metadata-Version: 2.1
Name: pyann
Version: 0.0.1
Summary: Python wrapper for Arya and Mount's ANN library (v1.1.3)
Home-page: http://github.com/annacnev/pyann
Author: Anna-Christina Nevison
Author-email: annanev@umich.edu
License: MIT
Platform: UNKNOWN
Requires-Python: >=3.6
Requires-Dist: numpy
Requires-Dist: pandas
